synaw_tools/__init__.py
synaw_tools/cipher.py
synaw_tools/ciphers.py
synaw_tools/cli.py
synaw_tools/template.py
synaw_tools/tools.py
synaw_tools/util.py
synaw_tools/var.py
synaw_tools-0.1.dist-info/LICENSE
synaw_tools-0.1.dist-info/METADATA
synaw_tools-0.1.dist-info/WHEEL
synaw_tools-0.1.dist-info/entry_points.txt
synaw_tools-0.1.dist-info/top_level.txt
synaw_tools-0.1.dist-info/RECORD
